{
"schemaName":"hc.ffqDetail.cls",
"onSave":"hc.ffqDetail.pls",
"properties":[


        {
        "name":"datastore",
        "type":"hidden",
        "valdn":"",
        "label":"",
        "flow":"",
        "value":"ffqCereals",
        "items":[
        
        ],
        "image":"",
        "lookup":{
        
        },
        "crossFlow":[
        
        ]},



        {
        "name":"memberId",
        "type":"hidden",
        "valdn":"",
        "label":"",
        "flow":"",
        "value":"$stateParams.memberId",
        "items":[
        
        ],
        "image":"",
        "lookup":{
        
        },
        "crossFlow":[
        
        ]},



        {
        "name":"jwari",
        "type":"ffq",
        "valdn":"",
        "label":"Bhakari (Jwari)",
        "flow":"",
        "value":"",
        "items":[
        
            {"text":"","value":"0"},
        
            {"text":"","value":"1"},
        
            {"text":"","value":"2"},
        
            {"text":"","value":"3"},
        
            {"text":"","value":"4"},
        
            {"text":"","value":"5"},
        
            {"text":"","value":"6"}
        
        ],
        "image":"",
        "lookup":{
        
        },
        "crossFlow":[
        
        ]},



        {
        "name":"makka",
        "type":"ffq",
        "valdn":"",
        "label":"Bhakari (Makka)",
        "flow":"",
        "value":"",
        "items":[
        
            {"text":"","value":"0"},
        
            {"text":"","value":"1"},
        
            {"text":"","value":"2"},
        
            {"text":"","value":"3"},
        
            {"text":"","value":"4"},
        
            {"text":"","value":"5"},
        
            {"text":"","value":"6"}
        
        ],
        "image":"",
        "lookup":{
        
        },
        "crossFlow":[
        
        ]},



        {
        "name":"chapati",
        "type":"ffq",
        "valdn":"",
        "label":"Chapati",
        "flow":"",
        "value":"",
        "items":[
        
            {"text":"","value":"0"},
        
            {"text":"","value":"1"},
        
            {"text":"","value":"2"},
        
            {"text":"","value":"3"},
        
            {"text":"","value":"4"},
        
            {"text":"","value":"5"},
        
            {"text":"","value":"6"}
        
        ],
        "image":"",
        "lookup":{
        
        },
        "crossFlow":[
        
        ]},



        {
        "name":"rice",
        "type":"ffq",
        "valdn":"",
        "label":"Rice",
        "flow":"",
        "value":"",
        "items":[
        
            {"text":"","value":"0"},
        
            {"text":"","value":"1"},
        
            {"text":"","value":"2"},
        
            {"text":"","value":"3"},
        
            {"text":"","value":"4"},
        
            {"text":"","value":"5"},
        
            {"text":"","value":"6"}
        
        ],
        "image":"",
        "lookup":{
        
        },
        "crossFlow":[
        
        ]}



]
}